phenomenal
