Metadata-Version: 1.1
Name: phenomenal
Version: 0.0.4
Summary: Phenomenal By Hery Phenomenal
Home-page: https://github.com/thitphavanh/HeryProfile
Author: Hery Phenomenal
Author-email: thitphavanh.psv@gmail.com
License: MIT
Download-URL: https://github.com/Thitphavanh/HeryProfile/archive/v0.0.4.zip
Keywords: Hery,Profile,Hery Phenomenal
Platform: UNKNOWN
Classifier: Development Status :: 3 - Alpha
Classifier: Intended Audience :: Education
Classifier: Topic :: Utilities
Classifier: License :: OSI Approved :: MIT License
Classifier: Programming Language :: Python :: 3
Classifier: Programming Language :: Python :: 3.4
Classifier: Programming Language :: Python :: 3.5
Classifier: Programming Language :: Python :: 3.6
Classifier: Programming Language :: Python :: 3.7
Classifier: Programming Language :: Python :: 3.8
Classifier: Programming Language :: Python :: 3.9
Classifier: Programming Language :: Python :: 3.10
